[{"place_id": 257000067, "licence": "Data \u00a9 OpenStreetMap contributors, ODbL 1.0. http://osm.org/copyright", "osm_type": "way", "osm_id": 270758558, "lat": "6.91269155", "lon": "122.07953692264576", "class": "office", "type": "government", "place_rank": 30, "importance": 5.855878538181151e-05, "addresstype": "office", "name": "Technical Educational Skills Development Authority - ARMM", "display_name": "Technical Educational Skills Development Authority - ARMM, Veterans Avenue, Zone IV, Santa Catalina, Zamboanga City, Zamboanga Peninsula, 7000, Philippines", "boundingbox": ["6.9125169", "6.9128661", "122.0794296", "122.0796442"], "geojson": {"type": "Polygon", "coordinates": [[[122.0794296, 6.9128544], [122.0794504, 6.9125169], [122.0796442, 6.9125287], [122.0796235, 6.9128661], [122.0794296, 6.9128544]]]}}, {"place_id": 255431151, "licence": "Data \u00a9 OpenStreetMap contributors, ODbL 1.0. http://osm.org/copyright", "osm_type": "way", "osm_id": 334984486, "lat": "7.19865955", "lon": "124.24672122146572", "class": "amenity", "type": "public_building", "place_rank": 30, "importance": 5.4464789806927866e-05, "addresstype": "amenity", "name": "DAR-ARMM", "display_name": "DAR-ARMM, G. Javier Street, Rosary Heights 6, Rosary Heights, Cotabato City, Bangsamoro, 9600, Philippines", "boundingbox": ["7.1985601", "7.1987858", "124.2465780", "124.2467912"], "geojson": {"type": "Polygon", "coordinates": [[[124.246578, 7.1987527], [124.2465955, 7.1986911], [124.2466544, 7.1987038], [124.2466735, 7.198628], [124.2466162, 7.1986138], [124.2466305, 7.1985601], [124.2467912, 7.1985964], [124.2467523, 7.1987681], [124.2467483, 7.1987858], [124.2467149, 7.1987793], [124.2466781, 7.1987722], [124.246578, 7.1987527]]]}}, {"place_id": 255354805, "licence": "Data \u00a9 OpenStreetMap contributors, ODbL 1.0. http://osm.org/copyright", "osm_type": "way", "osm_id": 335516782, "lat": "7.19623775", "lon": "124.24530232798926", "class": "building", "type": "public", "place_rank": 30, "importance": 5.4464789806927866e-05, "addresstype": "building", "name": "Bureau of Public Information ARMM", "display_name": "Bureau of Public Information ARMM, Governor Gutierrez Avenue, Rosary Heights 10, Rosary Heights, Cotabato City, Bangsamoro, 9600, Philippines", "boundingbox": ["7.1961679", "7.1963077", "124.2452360", "124.2453687"], "geojson": {"type": "Polygon", "coordinates": [[[124.245236, 7.1962141], [124.2452993, 7.1961679], [124.2453687, 7.1962614], [124.2453053, 7.1963077], [124.245236, 7.1962141]]]}}, {"place_id": 255669127, "licence": "Data \u00a9 OpenStreetMap contributors, ODbL 1.0. http://osm.org/copyright", "osm_type": "node", "osm_id": 1417971132, "lat": "7.1985467", "lon": "124.2456066", "class": "office", "type": "government", "place_rank": 30, "importance": 5.4464789806927866e-05, "addresstype": "office", "name": "Dep Ed - Armm", "display_name": "Dep Ed - Armm, Governor Gutierrez Avenue, Rosary Heights 6, Rosary Heights, Cotabato City, Bangsamoro, 9600, Philippines", "boundingbox": ["7.1984967", "7.1985967", "124.2455566", "124.2456566"], "geojson": {"type": "Point", "coordinates": [124.2456066, 7.1985467]}}, {"place_id": 255774596, "licence": "Data \u00a9 OpenStreetMap contributors, ODbL 1.0. http://osm.org/copyright", "osm_type": "way", "osm_id": 334984484, "lat": "7.1957762", "lon": "124.245635316439", "class": "building", "type": "office", "place_rank": 30, "importance": 5.4464789806927866e-05, "addresstype": "building", "name": "ARMM HEART", "display_name": "ARMM HEART, Governor Gutierrez Avenue, Rosary Heights 10, Rosary Heights, Cotabato City, Bangsamoro, 9600, Philippines", "boundingbox": ["7.1955976", "7.1959570", "124.2454283", "124.2458422"], "geojson": {"type": "Polygon", "coordinates": [[[124.2454283, 7.195803], [124.2457298, 7.1955976], [124.2458422, 7.1957494], [124.2455385, 7.195957], [124.2454283, 7.195803]]]}}, {"place_id": 255535604, "licence": "Data \u00a9 OpenStreetMap contributors, ODbL 1.0. http://osm.org/copyright", "osm_type": "way", "osm_id": 335517890, "lat": "7.1999212", "lon": "124.24695226183532", "class": "amenity", "type": "public_building", "place_rank": 30, "importance": 5.4464789806927866e-05, "addresstype": "amenity", "name": "Department of Health - ARMM", "display_name": "Department of Health - ARMM, G. Javier Street, Rosary Heights 6, Rosary Heights, Cotabato City, Bangsamoro, 9600, Philippines", "boundingbox": ["7.1997964", "7.2000459", "124.2468422", "124.2470623"], "geojson": {"type": "Polygon", "coordinates": [[[124.2468422, 7.1998571], [124.2469306, 7.1997964], [124.2470623, 7.1999853], [124.2469739, 7.2000459], [124.2468422, 7.1998571]]]}}, {"place_id": 255774720, "licence": "Data \u00a9 OpenStreetMap contributors, ODbL 1.0. http://osm.org/copyright", "osm_type": "way", "osm_id": 334996571, "lat": "7.1986954999999995", "lon": "124.24746576972144", "class": "building", "type": "office", "place_rank": 30, "importance": 5.4464789806927866e-05, "addresstype": "building", "name": "DSWD-ARMM", "display_name": "DSWD-ARMM, G. Javier Street, Rosary Heights 6, Rosary Heights, Cotabato City, Bangsamoro, 9600, Philippines", "boundingbox": ["7.1985636", "7.1988275", "124.2473173", "124.2476142"], "geojson": {"type": "Polygon", "coordinates": [[[124.2473173, 7.1987216], [124.2475368, 7.1985636], [124.2476142, 7.1986694], [124.2473948, 7.1988275], [124.2473173, 7.1987216]]]}}, {"place_id": 256322513, "licence": "Data \u00a9 OpenStreetMap contributors, ODbL 1.0. http://osm.org/copyright", "osm_type": "way", "osm_id": 247624801, "lat": "7.1969628", "lon": "124.24548635", "class": "building", "type": "yes", "place_rank": 30, "importance": 5.4464789806927866e-05, "addresstype": "building", "name": "Intelligence and Security Service, ARMM", "display_name": "Intelligence and Security Service, ARMM, Governor Gutierrez Avenue, Rosary Heights 6, Rosary Heights, Cotabato City, Bangsamoro, 9600, Philippines", "boundingbox": ["7.1968879", "7.1970377", "124.2454159", "124.2455568"], "geojson": {"type": "Polygon", "coordinates": [[[124.2454159, 7.1969352], [124.2454798, 7.1968879], [124.2455568, 7.1969904], [124.2454929, 7.1970377], [124.2454159, 7.1969352]]]}}, {"place_id": 256851174, "licence": "Data \u00a9 OpenStreetMap contributors, ODbL 1.0. http://osm.org/copyright", "osm_type": "way", "osm_id": 334980433, "lat": "7.19900715", "lon": "124.24525073935465", "class": "amenity", "type": "public_building", "place_rank": 30, "importance": 5.4464789806927866e-05, "addresstype": "amenity", "name": "DOST - ARMM RSTL", "display_name": "DOST - ARMM RSTL, R. Garcia Street, Rosary Heights 6, Rosary Heights, Cotabato City, Bangsamoro, 9600, Philippines", "boundingbox": ["7.1988911", "7.1991233", "124.2451443", "124.2453572"], "geojson": {"type": "Polygon", "coordinates": [[[124.2451443, 7.1989577], [124.2452392, 7.1988911], [124.2453572, 7.1990566], [124.2452623, 7.1991233], [124.2451443, 7.1989577]]]}}, {"place_id": 258988103, "licence": "Data \u00a9 OpenStreetMap contributors, ODbL 1.0. http://osm.org/copyright", "osm_type": "way", "osm_id": 335540047, "lat": "7.2003272", "lon": "124.24148466694979", "class": "building", "type": "yes", "place_rank": 30, "importance": 5.4464789806927866e-05, "addresstype": "building", "name": "PRADA ARMM", "display_name": "PRADA ARMM, Governor Gutierrez Avenue, Rosary Heights 10, Rosary Heights, Cotabato City, Bangsamoro, 9600, Philippines", "boundingbox": ["7.2001521", "7.2005023", "124.2413327", "124.2416366"], "geojson": {"type": "Polygon", "coordinates": [[[124.2413327, 7.2002374], [124.2414731, 7.2001521], [124.2416366, 7.200417], [124.2414963, 7.2005023], [124.2413327, 7.2002374]]]}}, {"place_id": 254794622, "licence": "Data \u00a9 OpenStreetMap contributors, ODbL 1.0. http://osm.org/copyright", "osm_type": "way", "osm_id": 334980059, "lat": "7.1992706", "lon": "124.24548110888804", "class": "amenity", "type": "public_building", "place_rank": 30, "importance": 5.4464789806927866e-05, "addresstype": "amenity", "name": "Department of Science and Technology - ARMM", "display_name": "Department of Science and Technology - ARMM, R. Garcia Street, Rosary Heights 6, Rosary Heights, Cotabato City, Bangsamoro, 9600, Philippines", "boundingbox": ["7.1991698", "7.1993713", "124.2453846", "124.2455776"], "geojson": {"type": "Polygon", "coordinates": [[[124.2453846, 7.1992391], [124.2454789, 7.1991698], [124.2455776, 7.1993021], [124.2454833, 7.1993713], [124.2453846, 7.1992391]]]}}, {"place_id": 255027312, "licence": "Data \u00a9 OpenStreetMap contributors, ODbL 1.0. http://osm.org/copyright", "osm_type": "way", "osm_id": 335515171, "lat": "7.1993201", "lon": "124.2458145297912", "class": "amenity", "type": "public_building", "place_rank": 30, "importance": 5.4464789806927866e-05, "addresstype": "amenity", "name": "Regional Planning & Development Office ARMM", "display_name": "Regional Planning & Development Office ARMM, G. Javier Street, Rosary Heights 6, Rosary Heights, Cotabato City, Bangsamoro, 9600, Philippines", "boundingbox": ["7.1991398", "7.1994668", "124.2456851", "124.2459857"], "geojson": {"type": "Polygon", "coordinates": [[[124.2456851, 7.1993794], [124.2457694, 7.1991822], [124.2458411, 7.1992134], [124.24587, 7.1991398], [124.2459644, 7.1991772], [124.2459555, 7.1992022], [124.2459857, 7.1992159], [124.2459681, 7.1992608], [124.2459493, 7.1992521], [124.2458524, 7.1994668], [124.2456964, 7.1994006], [124.2456989, 7.1993869], [124.2456851, 7.1993794]]]}}, {"place_id": 255698043, "licence": "Data \u00a9 OpenStreetMap contributors, ODbL 1.0. http://osm.org/copyright", "osm_type": "way", "osm_id": 334984491, "lat": "7.1983312999999995", "lon": "124.24686912207159", "class": "amenity", "type": "fire_station", "place_rank": 30, "importance": 5.4464789806927866e-05, "addresstype": "amenity", "name": "Bureau of Fire ARMM", "display_name": "Bureau of Fire ARMM, G. Javier Street, Rosary Heights 6, Rosary Heights, Cotabato City, Bangsamoro, 9600, Philippines", "boundingbox": ["7.1982050", "7.1985302", "124.2467260", "124.2469805"], "geojson": {"type": "Polygon", "coordinates": [[[124.246726, 7.1984355], [124.246893, 7.198205], [124.2469805, 7.1982729], [124.246893, 7.1983897], [124.2469376, 7.1984213], [124.2468533, 7.1985302], [124.246726, 7.1984355]]]}}, {"place_id": 255675459, "licence": "Data \u00a9 OpenStreetMap contributors, ODbL 1.0. http://osm.org/copyright", "osm_type": "way", "osm_id": 648193068, "lat": "7.3371186999999995", "lon": "124.24953908848948", "class": "amenity", "type": "school", "place_rank": 30, "importance": 4.754329747458637e-05, "addresstype": "amenity", "name": "ARMM Regional Science High School", "display_name": "ARMM Regional Science High School, Simuay-Landasan-Parang Road, Parang, Maguindanao del Norte, Bangsamoro, 9604, Philippines", "boundingbox": ["7.3368362", "7.3374165", "124.2490677", "124.2500562"], "geojson": {"type": "Polygon", "coordinates": [[[124.2490677, 7.3369337], [124.249866, 7.3368362], [124.2500562, 7.3373037], [124.2491448, 7.3374165], [124.2490677, 7.3369337]]]}}, {"place_id": 255341315, "licence": "Data \u00a9 OpenStreetMap contributors, ODbL 1.0. http://osm.org/copyright", "osm_type": "node", "osm_id": 1417053130, "lat": "7.2728324", "lon": "124.3136736", "class": "office", "type": "government", "place_rank": 30, "importance": 4.754329747458637e-05, "addresstype": "office", "name": "DPWH - ARMM", "display_name": "DPWH - ARMM, Davao-Cotabato National Highway, Crossing Simuay, Sultan Kudarat, Maguindanao del Norte, Bangsamoro, 9605, Philippines", "boundingbox": ["7.2727824", "7.2728824", "124.3136236", "124.3137236"], "geojson": {"type": "Point", "coordinates": [124.3136736, 7.2728324]}}, {"place_id": 257065510, "licence": "Data \u00a9 OpenStreetMap contributors, ODbL 1.0. http://osm.org/copyright", "osm_type": "node", "osm_id": 1417053126, "lat": "7.2730325", "lon": "124.3143898", "class": "amenity", "type": "public_building", "place_rank": 30, "importance": 4.754329747458637e-05, "addresstype": "amenity", "name": "ARMM Integrated Agricultural Research Center", "display_name": "ARMM Integrated Agricultural Research Center, Davao-Cotabato National Highway, Crossing Simuay, Sultan Kudarat, Maguindanao del Norte, Bangsamoro, 9605, Philippines", "boundingbox": ["7.2729825", "7.2730825", "124.3143398", "124.3144398"], "geojson": {"type": "Point", "coordinates": [124.3143898, 7.2730325]}}, {"place_id": 257046398, "licence": "Data \u00a9 OpenStreetMap contributors, ODbL 1.0. http://osm.org/copyright", "osm_type": "way", "osm_id": 337139579, "lat": "7.2506343", "lon": "124.27241914319231", "class": "office", "type": "government", "place_rank": 30, "importance": 4.754329747458637e-05, "addresstype": "office", "name": "TESDA ARMM", "display_name": "TESDA ARMM, Narciso Ramos Highway, Purok 6, Rebuken, Sultan Kudarat, Maguindanao del Norte, Bangsamoro, 9605, Philippines", "boundingbox": ["7.2500322", "7.2514054", "124.2715555", "124.2732777"], "geojson": {"type": "Polygon", "coordinates": [[[124.2715555, 7.2505001], [124.2730451, 7.2500322], [124.2732777, 7.2507685], [124.2724089, 7.2512593], [124.2718758, 7.2514054], [124.2715555, 7.2505001]]]}}, {"place_id": 254797785, "licence": "Data \u00a9 OpenStreetMap contributors, ODbL 1.0. http://osm.org/copyright", "osm_type": "node", "osm_id": 4739213824, "lat": "7.3858609", "lon": "124.2541693", "class": "office", "type": "telecommunication", "place_rank": 30, "importance": 4.5590142671809224e-05, "addresstype": "office", "name": "Pro ARMM Bts Colloc", "display_name": "Pro ARMM Bts Colloc, Narciso Ramos Highway, Malipayon, Making, Parang, Maguindanao del Norte, Bangsamoro, 9604, Philippines", "boundingbox": ["7.3858109", "7.3859109", "124.2541193", "124.2542193"], "geojson": {"type": "Point", "coordinates": [124.2541693, 7.3858609]}}, {"place_id": 257145352, "licence": "Data \u00a9 OpenStreetMap contributors, ODbL 1.0. http://osm.org/copyright", "osm_type": "node", "osm_id": 3428215037, "lat": "7.1779905", "lon": "124.2112688", "class": "amenity", "type": "public_building", "place_rank": 30, "importance": 3.750133516437045e-05, "addresstype": "amenity", "name": "DSWD-ARMM", "display_name": "DSWD-ARMM, Tapian-Lebak Coastal Road, Maguindanao del Norte, Bangsamoro, 9601, Philippines", "boundingbox": ["7.1779405", "7.1780405", "124.2112188", "124.2113188"], "geojson": {"type": "Point", "coordinates": [124.2112688, 7.1779905]}}, {"place_id": 255299631, "licence": "Data \u00a9 OpenStreetMap contributors, ODbL 1.0. http://osm.org/copyright", "osm_type": "node", "osm_id": 4201901390, "lat": "7.2365158", "lon": "124.2637692", "class": "office", "type": "government", "place_rank": 30, "importance": 4.754329747458637e-05, "addresstype": "office", "name": "Land Transportation Office", "display_name": "Land Transportation Office, Narciso Ramos Highway, Crossing Pinaring, Gang, Sultan Kudarat, Maguindanao del Norte, Bangsamoro, 9605, Philippines", "boundingbox": ["7.2364658", "7.2365658", "124.2637192", "124.2638192"], "geojson": {"type": "Point", "coordinates": [124.2637692, 7.2365158]}}, {"place_id": 255615978, "licence": "Data \u00a9 OpenStreetMap contributors, ODbL 1.0. http://osm.org/copyright", "osm_type": "way", "osm_id": 247624802, "lat": "7.19704765", "lon": "124.24517055000001", "class": "office", "type": "government", "place_rank": 30, "importance": 5.4464789806927866e-05, "addresstype": "office", "name": "Office of the Bangsamoro People", "display_name": "Office of the Bangsamoro People, Governor Gutierrez Avenue, Rosary Heights 6, Rosary Heights, Cotabato City, Bangsamoro, 9600, Philippines", "boundingbox": ["7.1967710", "7.1973243", "124.2449026", "124.2454385"], "geojson": {"type": "Polygon", "coordinates": [[[124.2449026, 7.1969708], [124.2451753, 7.196771], [124.2454385, 7.1971245], [124.2451658, 7.1973243], [124.2449026, 7.1969708]]]}}]